django_obfucat/__init__.py
django_obfucat/obfuscators.py
django_obfucat/utils.py
django_obfucat/management/__init__.py
django_obfucat/management/commands/__init__.py
django_obfucat/management/commands/obfucat_list.py
django_obfucat/management/commands/obfucat_obfuscate.py
django_obfucat/management/commands/obfucat_update.py
django_obfucat/management/commands/obfucat_validate.py
django_obfucat-0.0.10.dist-info/LICENSE
django_obfucat-0.0.10.dist-info/METADATA
django_obfucat-0.0.10.dist-info/WHEEL
django_obfucat-0.0.10.dist-info/top_level.txt
django_obfucat-0.0.10.dist-info/RECORD
