Metadata-Version: 2.1
Name: django-obfucat
Version: 0.0.10
Summary: Data obfuscation tool for GDPR-compliant development process
Home-page: https://bitbucket.org/3yourmind/django-obfucat
Author: Serhii Zavadskyi
Author-email: sz@3yourmind.com
License: MIT License
Platform: UNKNOWN
Classifier: Environment :: Web Environment
Classifier: Environment :: Console
Classifier: Development Status :: 4 - Beta
Classifier: Intended Audience :: Developers
Classifier: Intended Audience :: System Administrators
Classifier: License :: OSI Approved :: MIT License
Classifier: Operating System :: OS Independent
Classifier: Programming Language :: Python
Classifier: Programming Language :: Python :: 3.3
Classifier: Programming Language :: Python :: 3.4
Classifier: Programming Language :: Python :: 3.5
Classifier: Programming Language :: Python :: 3.6
Classifier: Programming Language :: Python :: 3.7
Classifier: Topic :: Database
Classifier: Topic :: Utilities
Requires-Dist: mimesis
